django_datalog/__init__.py
django_datalog/apps.py
django_datalog/facts.py
django_datalog/models.py
django_datalog/optimizer.py
django_datalog/query.py
django_datalog/rules.py
django_datalog/variables.py
django_datalog/migrations/__init__.py
django_datalog-0.3.1.dist-info/METADATA
django_datalog-0.3.1.dist-info/WHEEL
django_datalog-0.3.1.dist-info/licenses/LICENSE
django_datalog-0.3.1.dist-info/RECORD
