Metadata-Version: 2.4
Name: django-datalog
Version: 0.3.1
Summary: Django Datalog - Logic programming and inference engine for Django applications
Project-URL: Homepage, https://github.com/edelvalle/django-datalog
Project-URL: Documentation, https://django-datalog.readthedocs.io/
Project-URL: Repository, https://github.com/edelvalle/django-datalog.git
Project-URL: Issues, https://github.com/edelvalle/django-datalog/issues
Project-URL: Changelog, https://github.com/edelvalle/django-datalog/blob/main/CHANGELOG.md
Author-email: Eddy Ernesto del Valle Pino <eddy@edelvalle.me>
License-Expression: MIT
License-File: LICENSE
Keywords: datalog,django,facts,inference-engine,logic-programming,query,rules
Classifier: Development Status :: 4 - Beta
Classifier: Environment :: Web Environment
Classifier: Framework :: Django
Classifier: Framework :: Django :: 5.0
Classifier: Intended Audience :: Developers
Classifier: License :: OSI Approved :: MIT License
Classifier: Operating System :: OS Independent
Classifier: Programming Language :: Python
Classifier: Programming Language :: Python :: 3
Classifier: Programming Language :: Python :: 3.10
Classifier: Programming Language :: Python :: 3.11
Classifier: Programming Language :: Python :: 3.12
Classifier: Programming Language :: Python :: 3.13
Classifier: Topic :: Internet :: WWW/HTTP
Classifier: Topic :: Internet :: WWW/HTTP :: Dynamic Content
Classifier: Topic :: Software Development :: Libraries :: Application Frameworks
Classifier: Topic :: Software Development :: Libraries :: Python Modules
Requires-Python: >=3.12
Requires-Dist: django>=5
Requires-Dist: uuid6>=2024.1.12
Provides-Extra: dev
Requires-Dist: basedpyright>=1.12; extra == 'dev'
Requires-Dist: pytest-cov>=4.0; extra == 'dev'
Requires-Dist: pytest-django>=4.5; extra == 'dev'
Requires-Dist: pytest>=7.0; extra == 'dev'
Requires-Dist: ruff>=0.1; extra == 'dev'
Provides-Extra: docs
Requires-Dist: mkdocs-material>=9.0; extra == 'docs'
Requires-Dist: mkdocs>=1.5; extra == 'docs'
Requires-Dist: mkdocstrings[python]>=0.24; extra == 'docs'
Provides-Extra: test
Requires-Dist: pytest-cov>=4.0; extra == 'test'
Requires-Dist: pytest-django>=4.5; extra == 'test'
Requires-Dist: pytest>=7.0; extra == 'test'
